tarantool_utils
