Metadata-Version: 1.0
Name: tarantool-utils
Version: 0.1.5
Summary: Tarantool utils for Python
Home-page: https://github.com/toidi/tarantool-python-utils
Author: Iskandarov Eduard
Author-email: e.iskandarov@corp.mail.ru
License: BSD
Platform: UNKNOWN
